{
  "_fv": 43,
  "_type": "loottable",
  "definition": {
    "type": "Chest",
    "pools": [
      {
        "minrolls": 1,
        "maxrolls": 2,
        "minbonusrolls": 1,
        "maxbonusrolls": 1,
        "hasbonusrolls": false,
        "entries": [
          {
            "type": "item",
            "item": {
              "value": "CUSTOM:IcyFur"
            },
            "weight": 3,
            "minCount": 1,
            "maxCount": 3,
            "minEnchantmentLevel": 0,
            "maxEnchantmentLevel": 0,
            "affectedByFortune": false,
            "explosionDecay": false,
            "silkTouchMode": 0
          },
          {
            "type": "item",
            "item": {
              "value": "Items.SNOWBALL"
            },
            "weight": 5,
            "minCount": 1,
            "maxCount": 5,
            "minEnchantmentLevel": 0,
            "maxEnchantmentLevel": 0,
            "affectedByFortune": false,
            "explosionDecay": false,
            "silkTouchMode": 0
          }
        ]
      },
      {
        "minrolls": 1,
        "maxrolls": 2,
        "minbonusrolls": 1,
        "maxbonusrolls": 1,
        "hasbonusrolls": false,
        "entries": [
          {
            "type": "item",
            "item": {
              "value": "CUSTOM:SnowyBlueIce"
            },
            "weight": 3,
            "minCount": 1,
            "maxCount": 3,
            "minEnchantmentLevel": 0,
            "maxEnchantmentLevel": 0,
            "affectedByFortune": false,
            "explosionDecay": false,
            "silkTouchMode": 0
          },
          {
            "type": "item",
            "item": {
              "value": "Blocks.BLUE_ICE"
            },
            "weight": 5,
            "minCount": 1,
            "maxCount": 3,
            "minEnchantmentLevel": 0,
            "maxEnchantmentLevel": 0,
            "affectedByFortune": false,
            "explosionDecay": false,
            "silkTouchMode": 0
          }
        ]
      },
      {
        "minrolls": 1,
        "maxrolls": 2,
        "minbonusrolls": 1,
        "maxbonusrolls": 1,
        "hasbonusrolls": false,
        "entries": [
          {
            "type": "item",
            "item": {
              "value": "CUSTOM:BasaltBrick"
            },
            "weight": 2,
            "minCount": 1,
            "maxCount": 5,
            "minEnchantmentLevel": 0,
            "maxEnchantmentLevel": 0,
            "affectedByFortune": false,
            "explosionDecay": false,
            "silkTouchMode": 0
          },
          {
            "type": "item",
            "item": {
              "value": "CUSTOM:ScaryBasaltBrick"
            },
            "weight": 3,
            "minCount": 1,
            "maxCount": 3,
            "minEnchantmentLevel": 0,
            "maxEnchantmentLevel": 0,
            "affectedByFortune": false,
            "explosionDecay": false,
            "silkTouchMode": 0
          }
        ]
      }
    ],
    "name": "chests/icy_creature_tower_loot",
    "namespace": "minecraft"
  }
}